clibox.py
colors.py
py_cli_grid.py
py_cli_grid-0.1.0.dist-info/LICENSE.md
py_cli_grid-0.1.0.dist-info/METADATA
py_cli_grid-0.1.0.dist-info/WHEEL
py_cli_grid-0.1.0.dist-info/top_level.txt
py_cli_grid-0.1.0.dist-info/RECORD
