Metadata-Version: 2.1
Name: py-cli-grid
Version: 0.1.0
Summary: Package to manage CLI as a grid
Author-email: "Carlos G. Martín Pérez" <cagrmape@gmail.com>
Project-URL: Homepage, https://github.com/Carlosmape/py-cli-grid
Project-URL: Issues, https://github.com/Carlosmape/py-cli-grid/issues
Classifier: Programming Language :: Python :: 3
Classifier: License :: OSI Approved :: MIT License
Classifier: Operating System :: OS Independent
Requires-Python: >=3.10
License-File: LICENSE.md
